import java.io.InputStream;
import java.util.TimerTask;

// 
// Decompiled by Procyon v0.5.36
// 

final class g extends TimerTask implements Runnable
{
    private int I;
    C Code;
    static boolean Code;
    public B Code;
    int Code;
    private static g Code;
    private static boolean Z;
    static boolean I;
    private static g I;
    private static g Z;
    String Code;
    InputStream Code;
    private static Object Code;
    long Code;
    String I;
    String Z;
    String J;
    String B;
    String C;
    Object[] Code;
    d Code;
    private static boolean J;
    
    g(final int i) {
        this.I = i;
    }
    
    public final void run() {
        // 
        // This method could not be decompiled.
        // 
        // Original Bytecode:
        // 
        //     1: getfield        g.I:I
        //     4: tableswitch {
        //                0: 220
        //                1: 227
        //                2: 234
        //                3: 247
        //                4: 257
        //                5: 2930
        //                6: 319
        //                7: 2930
        //                8: 2930
        //                9: 2930
        //               10: 2930
        //               11: 2930
        //               12: 436
        //               13: 2930
        //               14: 2930
        //               15: 2930
        //               16: 2930
        //               17: 2930
        //               18: 2930
        //               19: 2930
        //               20: 2930
        //               21: 2930
        //               22: 2930
        //               23: 449
        //               24: 511
        //               25: 2930
        //               26: 2930
        //               27: 522
        //               28: 2930
        //               29: 2930
        //               30: 571
        //               31: 2084
        //               32: 2151
        //               33: 2227
        //               34: 2345
        //               35: 2395
        //               36: 2405
        //               37: 2420
        //               38: 2466
        //               39: 2493
        //               40: 2519
        //               41: 2527
        //               42: 2667
        //               43: 2735
        //               44: 2743
        //               45: 2762
        //               46: 2809
        //               47: 2824
        //               48: 2868
        //               49: 2875
        //          default: 2930
        //        }
        //   220: getstatic       Code.Code:LCode;
        //   223: invokevirtual   Code.a:()V
        //   226: return         
        //   227: getstatic       Code.Code:LCode;
        //   230: invokevirtual   Code.c:()V
        //   233: return         
        //   234: getstatic       Code.Code:LCode;
        //   237: invokevirtual   Code.i:()V
        //   240: getstatic       Code.Code:LCode;
        //   243: invokevirtual   Code.c:()V
        //   246: return         
        //   247: getstatic       Code.Code:LCode;
        //   250: getstatic       d.B:Ljava/lang/String;
        //   253: invokevirtual   Code.I:(Ljava/lang/String;)V
        //   256: return         
        //   257: getstatic       Code.Code:LCode;
        //   260: invokevirtual   Code.Code:()I
        //   263: dup            
        //   264: istore_1       
        //   265: ifeq            2930
        //   268: getstatic       Code.Code:LCode;
        //   271: new             Ljava/lang/StringBuffer;
        //   274: dup            
        //   275: invokespecial   java/lang/StringBuffer.<init>:()V
        //   278: ldc             "overlay:"
        //   280: invokevirtual   java/lang/StringBuffer.append:(Ljava/lang/String;)Ljava/lang/StringBuffer;
        //   283: bipush          76
        //   285: invokestatic    d.I:(I)Ljava/lang/String;
        //   288: invokevirtual   java/lang/StringBuffer.append:(Ljava/lang/String;)Ljava/lang/StringBuffer;
        //   291: invokevirtual   java/lang/StringBuffer.toString:()Ljava/lang/String;
        //   294: aconst_null    
        //   295: new             Ljava/lang/StringBuffer;
        //   298: dup            
        //   299: invokespecial   java/lang/StringBuffer.<init>:()V
        //   302: ldc             "a="
        //   304: invokevirtual   java/lang/StringBuffer.append:(Ljava/lang/String;)Ljava/lang/StringBuffer;
        //   307: iload_1        
        //   308: i2c            
        //   309: invokevirtual   java/lang/StringBuffer.append:(C)Ljava/lang/StringBuffer;
        //   312: invokevirtual   java/lang/StringBuffer.toString:()Ljava/lang/String;
        //   315: invokevirtual   Code.Code:(Ljava/lang/String;Ljava/lang/String;Ljava/lang/String;)V
        //   318: return         
        //   319: aload_0        
        //   320: getfield        g.Code:Ljava/lang/String;
        //   323: dup            
        //   324: astore_1       
        //   325: ifnull          349
        //   328: aload_1        
        //   329: ldc             "&url=rtsp://"
        //   331: invokevirtual   java/lang/String.indexOf:(Ljava/lang/String;)I
        //   334: iconst_m1      
        //   335: if_icmpeq       349
        //   338: aload_1        
        //   339: aload_1        
        //   340: ldc             "rtsp://"
        //   342: invokevirtual   java/lang/String.indexOf:(Ljava/lang/String;)I
        //   345: invokevirtual   java/lang/String.substring:(I)Ljava/lang/String;
        //   348: astore_1       
        //   349: getstatic       Browser.Code:LBrowser;
        //   352: aload_1        
        //   353: invokevirtual   javax/microedition/midlet/MIDlet.platformRequest:(Ljava/lang/String;)Z
        //   356: istore_2       
        //   357: getstatic       d.ab:Z
        //   360: ifne            387
        //   363: iload_2        
        //   364: ifne            387
        //   367: aload_1        
        //   368: ldc             ".jad"
        //   370: invokevirtual   java/lang/String.indexOf:(Ljava/lang/String;)I
        //   373: iconst_m1      
        //   374: if_icmpne       387
        //   377: aload_1        
        //   378: ldc             ".jar"
        //   380: invokevirtual   java/lang/String.indexOf:(Ljava/lang/String;)I
        //   383: iconst_m1      
        //   384: if_icmpeq       2930
        //   387: invokestatic    Browser.Code:()V
        //   390: return         
        //   391: pop            
        //   392: aload_0        
        //   393: getfield        g.Code:Ljava/lang/String;
        //   396: ldc             "&url=rtsp://"
        //   398: invokevirtual   java/lang/String.indexOf:(Ljava/lang/String;)I
        //   401: istore_2       
        //   402: aload_1        
        //   403: ldc             "rtsp://"
        //   405: invokevirtual   java/lang/String.startsWith:(Ljava/lang/String;)Z
        //   408: ifeq            2930
        //   411: iload_2        
        //   412: iconst_m1      
        //   413: if_icmpeq       2930
        //   416: aload_0        
        //   417: aload_0        
        //   418: getfield        g.Code:Ljava/lang/String;
        //   421: iconst_0       
        //   422: iload_2        
        //   423: invokevirtual   java/lang/String.substring:(II)Ljava/lang/String;
        //   426: putfield        g.Code:Ljava/lang/String;
        //   429: aload_0        
        //   430: invokevirtual   g.run:()V
        //   433: return         
        //   434: pop            
        //   435: return         
        //   436: getstatic       Browser.Code:Ljavax/microedition/lcdui/Display;
        //   439: getstatic       Browser.Code:Ljavax/microedition/lcdui/Display;
        //   442: invokevirtual   javax/microedition/lcdui/Display.getCurrent:()Ljavax/microedition/lcdui/Displayable;
        //   445: invokevirtual   javax/microedition/lcdui/Display.setCurrent:(Ljavax/microedition/lcdui/Displayable;)V
        //   448: return         
        //   449: getstatic       Browser.Code:Z
        //   452: ifne            2930
        //   455: aload_0        
        //   456: dup            
        //   457: astore_1       
        //   458: monitorenter   
        //   459: getstatic       g.Z:Z
        //   462: ifne            478
        //   465: aload_0        
        //   466: aconst_null    
        //   467: putfield        g.Code:LB;
        //   470: iconst_0       
        //   471: putstatic       g.Code:Z
        //   474: aload_0        
        //   475: invokevirtual   java/lang/Object.wait:()V
        //   478: iconst_0       
        //   479: putstatic       g.Z:Z
        //   482: aload_0        
        //   483: getfield        g.Code:LB;
        //   486: astore_2       
        //   487: aload_1        
        //   488: monitorexit    
        //   489: goto            497
        //   492: astore_2       
        //   493: aload_1        
        //   494: monitorexit    
        //   495: aload_2        
        //   496: athrow         
        //   497: aload_2        
        //   498: ifnull          449
        //   501: aload_2        
        //   502: getstatic       g.I:Z
        //   505: invokevirtual   B.Code:(Z)V
        //   508: goto            449
        //   511: iconst_1       
        //   512: putstatic       Code.c:Z
        //   515: getstatic       Code.Code:LCode;
        //   518: invokevirtual   Code.c:()V
        //   521: return         
        //   522: getstatic       Browser.Code:Z
        //   525: ifne            2930
        //   528: aload_0        
        //   529: dup            
        //   530: astore_1       
        //   531: monitorenter   
        //   532: getstatic       g.J:Z
        //   535: ifne            542
        //   538: aload_0        
        //   539: invokevirtual   java/lang/Object.wait:()V
        //   542: aload_1        
        //   543: monitorexit    
        //   544: goto            552
        //   547: astore_2       
        //   548: aload_1        
        //   549: monitorexit    
        //   550: aload_2        
        //   551: athrow         
        //   552: iconst_0       
        //   553: putstatic       g.J:Z
        //   556: getstatic       Code.Code:LCode;
        //   559: invokevirtual   javax/microedition/lcdui/Canvas.repaint:()V
        //   562: getstatic       Code.Code:LCode;
        //   565: invokevirtual   javax/microedition/lcdui/Canvas.serviceRepaints:()V
        //   568: goto            522
        //   571: getstatic       g.Code:Ljava/lang/Object;
        //   574: dup            
        //   575: astore_1       
        //   576: monitorenter   
        //   577: iconst_1       
        //   578: putstatic       Code.C:Z
        //   581: getstatic       Code.Code:LCode;
        //   584: invokevirtual   javax/microedition/lcdui/Canvas.repaint:()V
        //   587: new             Ljava/io/DataInputStream;
        //   590: dup            
        //   591: aload_0        
        //   592: getfield        g.Code:Ljava/io/InputStream;
        //   595: invokespecial   java/io/DataInputStream.<init>:(Ljava/io/InputStream;)V
        //   598: dup            
        //   599: astore_2       
        //   600: invokevirtual   java/io/DataInputStream.readUTF:()Ljava/lang/String;
        //   603: astore_3       
        //   604: aload_2        
        //   605: invokevirtual   java/io/DataInputStream.readUTF:()Ljava/lang/String;
        //   608: astore          4
        //   610: aload_2        
        //   611: invokevirtual   java/io/DataInputStream.readInt:()I
        //   614: istore          5
        //   616: aload_2        
        //   617: invokevirtual   java/io/DataInputStream.readByte:()B
        //   620: istore          6
        //   622: aload_2        
        //   623: invokevirtual   java/io/DataInputStream.readByte:()B
        //   626: dup            
        //   627: istore          7
        //   629: iconst_1       
        //   630: iand           
        //   631: istore          8
        //   633: iload           7
        //   635: iconst_2       
        //   636: iand           
        //   637: dup            
        //   638: ineg           
        //   639: ior            
        //   640: bipush          31
        //   642: iushr          
        //   643: istore          9
        //   645: iload           7
        //   647: bipush          8
        //   649: iand           
        //   650: dup            
        //   651: ineg           
        //   652: ior            
        //   653: bipush          31
        //   655: iushr          
        //   656: istore          10
        //   658: aconst_null    
        //   659: astore          11
        //   661: aconst_null    
        //   662: astore          12
        //   664: iload           10
        //   666: ifeq            681
        //   669: aload_2        
        //   670: invokevirtual   java/io/DataInputStream.readUTF:()Ljava/lang/String;
        //   673: astore          12
        //   675: aload_2        
        //   676: invokevirtual   java/io/DataInputStream.readUTF:()Ljava/lang/String;
        //   679: astore          11
        //   681: aload_2        
        //   682: invokevirtual   java/io/DataInputStream.readShort:()S
        //   685: istore          13
        //   687: iload           6
        //   689: bipush          69
        //   691: if_icmpne       764
        //   694: iconst_0       
        //   695: putstatic       Code.Z:Z
        //   698: ldc             ""
        //   700: putstatic       Code.Z:Ljava/lang/String;
        //   703: iconst_0       
        //   704: putstatic       d.I:Z
        //   707: invokestatic    Code.Code:()Ld;
        //   710: dup            
        //   711: astore_2       
        //   712: getfield        d.Code:LB;
        //   715: getfield        B.Code:Ljava/lang/String;
        //   718: invokestatic    d.Code:(Ljava/lang/String;)I
        //   721: istore_3       
        //   722: aload_2        
        //   723: invokevirtual   d.Code:()LB;
        //   726: ifnonnull       744
        //   729: iload_3        
        //   730: bipush          65
        //   732: if_icmpne       744
        //   735: aload_2        
        //   736: iconst_1       
        //   737: putfield        d.J:Z
        //   740: aload_2        
        //   741: invokevirtual   d.Z:()V
        //   744: aload_0        
        //   745: getfield        g.Code:Ljava/io/InputStream;
        //   748: invokevirtual   java/io/InputStream.close:()V
        //   751: iconst_0       
        //   752: putstatic       Code.C:Z
        //   755: getstatic       Code.Code:LCode;
        //   758: invokevirtual   javax/microedition/lcdui/Canvas.repaint:()V
        //   761: aload_1        
        //   762: monitorexit    
        //   763: return         
        //   764: iconst_0       
        //   765: istore          14
        //   767: aconst_null    
        //   768: astore          15
        //   770: aconst_null    
        //   771: astore          16
        //   773: new             Ljava/util/Vector;
        //   776: dup            
        //   777: invokespecial   java/util/Vector.<init>:()V
        //   780: astore          17
        //   782: getstatic       Code.J:Z
        //   785: ifne            1775
        //   788: getstatic       Code.B:Ljava/lang/String;
        //   791: aload_3        
        //   792: invokevirtual   java/lang/String.equals:(Ljava/lang/Object;)Z
        //   795: ifeq            1775
        //   798: iload           5
        //   800: getstatic       Code.Code:I
        //   803: if_icmpeq       820
        //   806: iload           5
        //   808: ifne            1775
        //   811: getstatic       Code.Code:I
        //   814: getstatic       Code.I:I
        //   817: if_icmpne       1775
        //   820: iload           9
        //   822: ifeq            970
        //   825: iload           6
        //   827: bipush          68
        //   829: if_icmpne       849
        //   832: new             Ljava/util/Vector;
        //   835: dup            
        //   836: iload           13
        //   838: invokespecial   java/util/Vector.<init>:(I)V
        //   841: astore          15
        //   843: iconst_1       
        //   844: istore          14
        //   846: goto            965
        //   849: new             Ljava/util/Vector;
        //   852: dup            
        //   853: getstatic       d.J:Ljava/util/Vector;
        //   856: invokevirtual   java/util/Vector.size:()I
        //   859: invokespecial   java/util/Vector.<init>:(I)V
        //   862: astore          15
        //   864: iconst_0       
        //   865: istore          18
        //   867: iload           18
        //   869: getstatic       d.J:Ljava/util/Vector;
        //   872: invokevirtual   java/util/Vector.size:()I
        //   875: if_icmpge       965
        //   878: getstatic       d.J:Ljava/util/Vector;
        //   881: iload           18
        //   883: invokevirtual   java/util/Vector.elementAt:(I)Ljava/lang/Object;
        //   886: checkcast       [Ljava/lang/Object;
        //   889: invokestatic    d.Code:([Ljava/lang/Object;)[Ljava/lang/Object;
        //   892: dup            
        //   893: astore          19
        //   895: iconst_5       
        //   896: invokestatic    d.Code:([Ljava/lang/Object;I)I
        //   899: dup            
        //   900: istore          20
        //   902: bipush          82
        //   904: if_icmpne       916
        //   907: iconst_1       
        //   908: istore          14
        //   910: iinc            18, 1
        //   913: goto            867
        //   916: iload           20
        //   918: bipush          83
        //   920: if_icmpeq       952
        //   923: aload           19
        //   925: iconst_5       
        //   926: new             Ljava/lang/Integer;
        //   929: dup            
        //   930: bipush          83
        //   932: invokespecial   java/lang/Integer.<init>:(I)V
        //   935: aastore        
        //   936: aload           19
        //   938: bipush          6
        //   940: new             Ljava/lang/Integer;
        //   943: dup            
        //   944: iconst_0       
        //   945: invokespecial   java/lang/Integer.<init>:(I)V
        //   948: aastore        
        //   949: iconst_1       
        //   950: istore          14
        //   952: aload           15
        //   954: aload           19
        //   956: invokevirtual   java/util/Vector.addElement:(Ljava/lang/Object;)V
        //   959: iinc            18, 1
        //   962: goto            867
        //   965: aload           15
        //   967: invokestatic    d.Code:(Ljava/util/Vector;)V
        //   970: iload           8
        //   972: ifeq            1103
        //   975: new             Ljava/util/Vector;
        //   978: dup            
        //   979: bipush          9
        //   981: invokespecial   java/util/Vector.<init>:(I)V
        //   984: astore          16
        //   986: iconst_0       
        //   987: istore          18
        //   989: iload           18
        //   991: bipush          9
        //   993: if_icmpge       1103
        //   996: getstatic       d.a:Ljava/util/Vector;
        //   999: iload           18
        //  1001: invokestatic    d.Code:(Ljava/util/Vector;I)[Ljava/lang/Object;
        //  1004: bipush          9
        //  1006: invokestatic    d.Code:([Ljava/lang/Object;I)I
        //  1009: iconst_2       
        //  1010: iand           
        //  1011: ifeq            1022
        //  1014: invokestatic    d.Code:()[Ljava/lang/Object;
        //  1017: astore          19
        //  1019: goto            1077
        //  1022: iload           6
        //  1024: bipush          68
        //  1026: if_icmpne       1037
        //  1029: invokestatic    d.Code:()[Ljava/lang/Object;
        //  1032: astore          19
        //  1034: goto            1050
        //  1037: getstatic       d.a:Ljava/util/Vector;
        //  1040: iload           18
        //  1042: invokestatic    d.Code:(Ljava/util/Vector;I)[Ljava/lang/Object;
        //  1045: invokestatic    d.Code:([Ljava/lang/Object;)[Ljava/lang/Object;
        //  1048: astore          19
        //  1050: aload           19
        //  1052: iconst_5       
        //  1053: invokestatic    d.Code:([Ljava/lang/Object;I)I
        //  1056: bipush          83
        //  1058: if_icmpeq       1077
        //  1061: aload           19
        //  1063: bipush          6
        //  1065: new             Ljava/lang/Integer;
        //  1068: dup            
        //  1069: iconst_0       
        //  1070: invokespecial   java/lang/Integer.<init>:(I)V
        //  1073: aastore        
        //  1074: iconst_1       
        //  1075: istore          14
        //  1077: aload           19
        //  1079: iconst_5       
        //  1080: new             Ljava/lang/Integer;
        //  1083: dup            
        //  1084: bipush          83
        //  1086: invokespecial   java/lang/Integer.<init>:(I)V
        //  1089: aastore        
        //  1090: aload           16
        //  1092: aload           19
        //  1094: invokevirtual   java/util/Vector.addElement:(Ljava/lang/Object;)V
        //  1097: iinc            18, 1
        //  1100: goto            989
        //  1103: iconst_1       
        //  1104: istore          6
        //  1106: iload           6
        //  1108: iload           13
        //  1110: if_icmpgt       1642
        //  1113: iconst_1       
        //  1114: istore          14
        //  1116: aload_2        
        //  1117: invokevirtual   java/io/DataInputStream.readByte:()B
        //  1120: istore          18
        //  1122: aload_2        
        //  1123: invokevirtual   java/io/DataInputStream.readByte:()B
        //  1126: istore          19
        //  1128: aload_2        
        //  1129: invokevirtual   java/io/DataInputStream.readByte:()B
        //  1132: istore          20
        //  1134: iconst_m1      
        //  1135: istore          21
        //  1137: iload           18
        //  1139: ifne            1202
        //  1142: bipush          16
        //  1144: newarray        B
        //  1146: astore          22
        //  1148: aload_2        
        //  1149: aload           22
        //  1151: invokevirtual   java/io/DataInputStream.readFully:([B)V
        //  1154: aload           15
        //  1156: aload           22
        //  1158: iconst_0       
        //  1159: invokestatic    d.Code:(Ljava/util/Vector;[BZ)I
        //  1162: dup            
        //  1163: istore          21
        //  1165: iconst_m1      
        //  1166: if_icmpeq       1186
        //  1169: aload           15
        //  1171: iload           21
        //  1173: invokevirtual   java/util/Vector.elementAt:(I)Ljava/lang/Object;
        //  1176: checkcast       [Ljava/lang/Object;
        //  1179: astore          23
        //  1181: bipush          16
        //  1183: goto            1253
        //  1186: invokestatic    d.Code:()[Ljava/lang/Object;
        //  1189: dup            
        //  1190: astore          23
        //  1192: bipush          7
        //  1194: aload           22
        //  1196: aastore        
        //  1197: bipush          16
        //  1199: goto            1253
        //  1202: iload           18
        //  1204: bipush          10
        //  1206: if_icmpge       1233
        //  1209: iload           8
        //  1211: ifeq            1233
        //  1214: aload           16
        //  1216: iload           18
        //  1218: iconst_1       
        //  1219: isub           
        //  1220: invokevirtual   java/util/Vector.elementAt:(I)Ljava/lang/Object;
        //  1223: checkcast       [Ljava/lang/Object;
        //  1226: astore          23
        //  1228: bipush          16
        //  1230: goto            1253
        //  1233: aload_0        
        //  1234: getfield        g.Code:Ljava/io/InputStream;
        //  1237: invokevirtual   java/io/InputStream.close:()V
        //  1240: iconst_0       
        //  1241: putstatic       Code.C:Z
        //  1244: getstatic       Code.Code:LCode;
        //  1247: invokevirtual   javax/microedition/lcdui/Canvas.repaint:()V
        //  1250: aload_1        
        //  1251: monitorexit    
        //  1252: return         
        //  1253: newarray        B
        //  1255: astore          22
        //  1257: iload           20
        //  1259: iconst_2       
        //  1260: iand           
        //  1261: ifeq            1270
        //  1264: aload_2        
        //  1265: aload           22
        //  1267: invokevirtual   java/io/DataInputStream.readFully:([B)V
        //  1270: iload           20
        //  1272: iconst_4       
        //  1273: iand           
        //  1274: ifeq            1288
        //  1277: aload           23
        //  1279: iconst_0       
        //  1280: aload_2        
        //  1281: invokevirtual   java/io/DataInputStream.readUTF:()Ljava/lang/String;
        //  1284: aastore        
        //  1285: goto            1294
        //  1288: aload           23
        //  1290: iconst_0       
        //  1291: ldc             ""
        //  1293: aastore        
        //  1294: iload           20
        //  1296: bipush          8
        //  1298: iand           
        //  1299: ifeq            1313
        //  1302: aload           23
        //  1304: iconst_1       
        //  1305: aload_2        
        //  1306: invokevirtual   java/io/DataInputStream.readUTF:()Ljava/lang/String;
        //  1309: aastore        
        //  1310: goto            1319
        //  1313: aload           23
        //  1315: iconst_1       
        //  1316: ldc             ""
        //  1318: aastore        
        //  1319: iload           20
        //  1321: bipush          16
        //  1323: iand           
        //  1324: ifeq            1362
        //  1327: aload_2        
        //  1328: invokevirtual   java/io/DataInputStream.readShort:()S
        //  1331: istore          24
        //  1333: aconst_null    
        //  1334: astore          25
        //  1336: iload           24
        //  1338: ifle            1353
        //  1341: iload           24
        //  1343: newarray        B
        //  1345: astore          25
        //  1347: aload_2        
        //  1348: aload           25
        //  1350: invokevirtual   java/io/DataInputStream.readFully:([B)V
        //  1353: aload           23
        //  1355: iconst_2       
        //  1356: aload           25
        //  1358: aastore        
        //  1359: goto            1367
        //  1362: aload           23
        //  1364: iconst_2       
        //  1365: aconst_null    
        //  1366: aastore        
        //  1367: iload           18
        //  1369: ifne            1565
        //  1372: iconst_m1      
        //  1373: istore          18
        //  1375: iconst_m1      
        //  1376: istore          24
        //  1378: iload           20
        //  1380: iconst_2       
        //  1381: iand           
        //  1382: ifne            1392
        //  1385: iload           19
        //  1387: bipush          82
        //  1389: if_icmpne       1418
        //  1392: aload           15
        //  1394: aload           22
        //  1396: iconst_1       
        //  1397: invokestatic    d.Code:(Ljava/util/Vector;[BZ)I
        //  1400: istore          18
        //  1402: aload           15
        //  1404: aload           23
        //  1406: bipush          7
        //  1408: aaload         
        //  1409: checkcast       [B
        //  1412: iconst_1       
        //  1413: invokestatic    d.Code:(Ljava/util/Vector;[BZ)I
        //  1416: istore          24
        //  1418: iload           24
        //  1420: iconst_m1      
        //  1421: if_icmpeq       1448
        //  1424: iload           21
        //  1426: iconst_m1      
        //  1427: if_icmpeq       1448
        //  1430: aload           15
        //  1432: iload           24
        //  1434: invokevirtual   java/util/Vector.elementAt:(I)Ljava/lang/Object;
        //  1437: checkcast       [Ljava/lang/Object;
        //  1440: bipush          8
        //  1442: aload           23
        //  1444: bipush          8
        //  1446: aaload         
        //  1447: aastore        
        //  1448: iload           18
        //  1450: iconst_m1      
        //  1451: if_icmpeq       1479
        //  1454: iload           19
        //  1456: bipush          82
        //  1458: if_icmpeq       1479
        //  1461: aload           15
        //  1463: iload           18
        //  1465: invokevirtual   java/util/Vector.elementAt:(I)Ljava/lang/Object;
        //  1468: checkcast       [Ljava/lang/Object;
        //  1471: bipush          8
        //  1473: aload           23
        //  1475: bipush          7
        //  1477: aaload         
        //  1478: aastore        
        //  1479: iload           19
        //  1481: bipush          65
        //  1483: if_icmpeq       1493
        //  1486: iload           19
        //  1488: bipush          77
        //  1490: if_icmpne       1542
        //  1493: aload           23
        //  1495: iconst_5       
        //  1496: new             Ljava/lang/Integer;
        //  1499: dup            
        //  1500: bipush          83
        //  1502: invokespecial   java/lang/Integer.<init>:(I)V
        //  1505: aastore        
        //  1506: aload           23
        //  1508: bipush          6
        //  1510: new             Ljava/lang/Integer;
        //  1513: dup            
        //  1514: iconst_0       
        //  1515: invokespecial   java/lang/Integer.<init>:(I)V
        //  1518: aastore        
        //  1519: aload           23
        //  1521: bipush          8
        //  1523: aload           22
        //  1525: aastore        
        //  1526: iload           21
        //  1528: iconst_m1      
        //  1529: if_icmpne       1636
        //  1532: aload           15
        //  1534: aload           23
        //  1536: invokevirtual   java/util/Vector.addElement:(Ljava/lang/Object;)V
        //  1539: goto            1636
        //  1542: iload           19
        //  1544: bipush          82
        //  1546: if_icmpne       1636
        //  1549: iload           21
        //  1551: iconst_m1      
        //  1552: if_icmpeq       1636
        //  1555: aload           15
        //  1557: iload           21
        //  1559: invokevirtual   java/util/Vector.removeElementAt:(I)V
        //  1562: goto            1636
        //  1565: iload           18
        //  1567: bipush          10
        //  1569: if_icmpge       1636
        //  1572: iload           8
        //  1574: ifeq            1636
        //  1577: iload           19
        //  1579: bipush          82
        //  1581: if_icmpne       1615
        //  1584: invokestatic    d.Code:()[Ljava/lang/Object;
        //  1587: dup            
        //  1588: astore          19
        //  1590: iconst_5       
        //  1591: new             Ljava/lang/Integer;
        //  1594: dup            
        //  1595: bipush          83
        //  1597: invokespecial   java/lang/Integer.<init>:(I)V
        //  1600: aastore        
        //  1601: aload           16
        //  1603: aload           19
        //  1605: iload           18
        //  1607: iconst_1       
        //  1608: isub           
        //  1609: invokevirtual   java/util/Vector.setElementAt:(Ljava/lang/Object;I)V
        //  1612: goto            1636
        //  1615: aload           23
        //  1617: invokestatic    d.Code:([Ljava/lang/Object;)Z
        //  1620: ifne            1636
        //  1623: aload           23
        //  1625: bipush          9
        //  1627: new             Ljava/lang/Integer;
        //  1630: dup            
        //  1631: iconst_1       
        //  1632: invokespecial   java/lang/Integer.<init>:(I)V
        //  1635: aastore        
        //  1636: iinc            6, 1
        //  1639: goto            1106
        //  1642: iload           9
        //  1644: ifeq            1653
        //  1647: aload           15
        //  1649: invokestatic    d.Code:(Ljava/util/Vector;)Z
        //  1652: pop            
        //  1653: iload           8
        //  1655: ifeq            1788
        //  1658: iconst_0       
        //  1659: istore_2       
        //  1660: iload_2        
        //  1661: bipush          9
        //  1663: if_icmpge       1788
        //  1666: getstatic       d.a:Ljava/util/Vector;
        //  1669: iload_2        
        //  1670: invokestatic    d.Code:(Ljava/util/Vector;I)[Ljava/lang/Object;
        //  1673: bipush          9
        //  1675: invokestatic    d.Code:([Ljava/lang/Object;I)I
        //  1678: iconst_2       
        //  1679: iand           
        //  1680: ifeq            1769
        //  1683: aload           16
        //  1685: iload_2        
        //  1686: invokestatic    d.Code:(Ljava/util/Vector;I)[Ljava/lang/Object;
        //  1689: invokestatic    d.Code:([Ljava/lang/Object;)Z
        //  1692: ifeq            1751
        //  1695: getstatic       d.a:Ljava/util/Vector;
        //  1698: iload_2        
        //  1699: invokestatic    d.Code:(Ljava/util/Vector;I)[Ljava/lang/Object;
        //  1702: invokestatic    d.Code:([Ljava/lang/Object;)[Ljava/lang/Object;
        //  1705: astore          6
        //  1707: iload           14
        //  1709: aload           6
        //  1711: iconst_5       
        //  1712: invokestatic    d.Code:([Ljava/lang/Object;I)I
        //  1715: bipush          83
        //  1717: isub           
        //  1718: dup            
        //  1719: ineg           
        //  1720: ior            
        //  1721: bipush          31
        //  1723: iushr          
        //  1724: ior            
        //  1725: istore          14
        //  1727: aload           6
        //  1729: iconst_5       
        //  1730: new             Ljava/lang/Integer;
        //  1733: dup            
        //  1734: bipush          83
        //  1736: invokespecial   java/lang/Integer.<init>:(I)V
        //  1739: aastore        
        //  1740: aload           16
        //  1742: aload           6
        //  1744: iload_2        
        //  1745: invokevirtual   java/util/Vector.setElementAt:(Ljava/lang/Object;I)V
        //  1748: goto            1769
        //  1751: iconst_1       
        //  1752: istore          14
        //  1754: aload           17
        //  1756: getstatic       d.a:Ljava/util/Vector;
        //  1759: iload_2        
        //  1760: invokestatic    d.Code:(Ljava/util/Vector;I)[Ljava/lang/Object;
        //  1763: bipush          10
        //  1765: aaload         
        //  1766: invokevirtual   java/util/Vector.addElement:(Ljava/lang/Object;)V
        //  1769: iinc            2, 1
        //  1772: goto            1660
        //  1775: iconst_1       
        //  1776: putstatic       Code.B:Z
        //  1779: getstatic       Code.Code:Lg;
        //  1782: ifnonnull       1788
        //  1785: invokestatic    g.I:()V
        //  1788: aload_0        
        //  1789: getfield        g.Code:Ljava/io/InputStream;
        //  1792: invokevirtual   java/io/InputStream.close:()V
        //  1795: getstatic       Code.J:Z
        //  1798: ifne            2036
        //  1801: getstatic       Code.B:Ljava/lang/String;
        //  1804: aload_3        
        //  1805: invokevirtual   java/lang/String.equals:(Ljava/lang/Object;)Z
        //  1808: ifeq            2036
        //  1811: iload           5
        //  1813: getstatic       Code.Code:I
        //  1816: if_icmpeq       1833
        //  1819: iload           5
        //  1821: ifne            2036
        //  1824: getstatic       Code.Code:I
        //  1827: getstatic       Code.I:I
        //  1830: if_icmpne       2036
        //  1833: iload           14
        //  1835: ifeq            1898
        //  1838: iload           9
        //  1840: ifeq            1853
        //  1843: aload           15
        //  1845: dup            
        //  1846: putstatic       d.J:Ljava/util/Vector;
        //  1849: iconst_0       
        //  1850: invokestatic    d.Code:(Ljava/util/Vector;Z)V
        //  1853: iload           8
        //  1855: ifeq            1898
        //  1858: aload           16
        //  1860: dup            
        //  1861: putstatic       d.a:Ljava/util/Vector;
        //  1864: iconst_0       
        //  1865: invokestatic    d.Code:(Ljava/util/Vector;Z)V
        //  1868: iconst_0       
        //  1869: istore_2       
        //  1870: iload_2        
        //  1871: aload           17
        //  1873: invokevirtual   java/util/Vector.size:()I
        //  1876: if_icmpge       1898
        //  1879: aload           17
        //  1881: iload_2        
        //  1882: invokevirtual   java/util/Vector.elementAt:(I)Ljava/lang/Object;
        //  1885: checkcast       Ljava/lang/Integer;
        //  1888: iconst_0       
        //  1889: invokestatic    Code.Code:(Ljava/lang/Integer;Z)V
        //  1892: iinc            2, 1
        //  1895: goto            1870
        //  1898: iload           10
        //  1900: ifeq            1940
        //  1903: aload           12
        //  1905: dup            
        //  1906: putstatic       Code.Z:Ljava/lang/String;
        //  1909: invokevirtual   java/lang/String.length:()I
        //  1912: ifle            1919
        //  1915: iconst_1       
        //  1916: goto            1920
        //  1919: iconst_0       
        //  1920: dup            
        //  1921: putstatic       Code.Z:Z
        //  1924: ifeq            1940
        //  1927: aload           11
        //  1929: putstatic       Code.J:Ljava/lang/String;
        //  1932: iload           7
        //  1934: bipush          7
        //  1936: iand           
        //  1937: putstatic       Code.J:I
        //  1940: iload           5
        //  1942: ifeq            1950
        //  1945: iload           5
        //  1947: putstatic       Code.I:I
        //  1950: aload           4
        //  1952: putstatic       Code.B:Ljava/lang/String;
        //  1955: iconst_0       
        //  1956: putstatic       Code.B:Z
        //  1959: iconst_0       
        //  1960: invokestatic    d.J:(Z)V
        //  1963: iload           14
        //  1965: ifne            1973
        //  1968: iload           10
        //  1970: ifeq            2036
        //  1973: iconst_0       
        //  1974: bipush          90
        //  1976: iconst_0       
        //  1977: invokestatic    Code.Code:(IZ)Z
        //  1980: ior            
        //  1981: bipush          91
        //  1983: iconst_0       
        //  1984: invokestatic    Code.Code:(IZ)Z
        //  1987: ior            
        //  1988: istore_2       
        //  1989: bipush          65
        //  1991: iload           10
        //  1993: invokestatic    Code.Code:(IZ)Z
        //  1996: pop            
        //  1997: bipush          68
        //  1999: iconst_0       
        //  2000: invokestatic    Code.Code:(IZ)Z
        //  2003: pop            
        //  2004: bipush          76
        //  2006: iconst_0       
        //  2007: invokestatic    Code.Code:(IZ)Z
        //  2010: pop            
        //  2011: bipush          123
        //  2013: invokestatic    d.I:(I)Ljava/lang/String;
        //  2016: invokestatic    Code.Code:(Ljava/lang/String;)Ld;
        //  2019: dup            
        //  2020: astore_3       
        //  2021: ifnull          2036
        //  2024: iload_2        
        //  2025: ifeq            2036
        //  2028: getstatic       Code.Code:LCode;
        //  2031: aload_3        
        //  2032: invokevirtual   Code.I:(Ld;)Z
        //  2035: pop            
        //  2036: aload_0        
        //  2037: getfield        g.Code:Ljava/io/InputStream;
        //  2040: invokevirtual   java/io/InputStream.close:()V
        //  2043: iconst_0       
        //  2044: putstatic       Code.C:Z
        //  2047: getstatic       Code.Code:LCode;
        //  2050: invokevirtual   javax/microedition/lcdui/Canvas.repaint:()V
        //  2053: goto            2076
        //  2056: astore_2       
        //  2057: aload_0        
        //  2058: getfield        g.Code:Ljava/io/InputStream;
        //  2061: invokevirtual   java/io/InputStream.close:()V
        //  2064: iconst_0       
        //  2065: putstatic       Code.C:Z
        //  2068: getstatic       Code.Code:LCode;
        //  2071: invokevirtual   javax/microedition/lcdui/Canvas.repaint:()V
        //  2074: aload_2        
        //  2075: athrow         
        //  2076: aload_1        
        //  2077: monitorexit    
        //  2078: return         
        //  2079: astore_2       
        //  2080: aload_1        
        //  2081: monitorexit    
        //  2082: aload_2        
        //  2083: athrow         
        //  2084: iconst_1       
        //  2085: putstatic       Code.a:Z
        //  2088: getstatic       Code.Code:LCode;
        //  2091: invokevirtual   javax/microedition/lcdui/Canvas.repaint:()V
        //  2094: aload_0        
        //  2095: getfield        g.Code:Ld;
        //  2098: invokestatic    B.Code:(Ld;)V
        //  2101: bipush          110
        //  2103: anewarray       Ljava/lang/Object;
        //  2106: astore_1       
        //  2107: bipush          110
        //  2109: newarray        I
        //  2111: astore_2       
        //  2112: aload_1        
        //  2113: bipush          53
        //  2115: ldc             "myopera:async"
        //  2117: aastore        
        //  2118: aload_1        
        //  2119: aload_2        
        //  2120: ldc             "myopera:async"
        //  2122: aconst_null    
        //  2123: invokestatic    d.Code:(Ljava/lang/String;Ljava/lang/String;)I
        //  2126: invokestatic    d.Code:([Ljava/lang/Object;[II)Lf;
        //  2129: ldc2_w          2147483647
        //  2132: invokevirtual   java/io/InputStream.skip:(J)J
        //  2135: pop2           
        //  2136: goto            2140
        //  2139: pop            
        //  2140: iconst_0       
        //  2141: putstatic       Code.a:Z
        //  2144: getstatic       Code.Code:LCode;
        //  2147: invokevirtual   javax/microedition/lcdui/Canvas.repaint:()V
        //  2150: return         
        //  2151: getstatic       Code.Code:Lg;
        //  2154: aload_0        
        //  2155: if_acmpeq       2164
        //  2158: aload_0        
        //  2159: invokevirtual   java/util/TimerTask.cancel:()Z
        //  2162: pop            
        //  2163: return         
        //  2164: getstatic       Code.B:Z
        //  2167: ifne            2189
        //  2170: getstatic       Code.Code:I
        //  2173: getstatic       Code.I:I
        //  2176: if_icmpne       2189
        //  2179: aconst_null    
        //  2180: putstatic       Code.Code:Lg;
        //  2183: aload_0        
        //  2184: invokevirtual   java/util/TimerTask.cancel:()Z
        //  2187: pop            
        //  2188: return         
        //  2189: getstatic       Code.J:Z
        //  2192: ifne            2930
        //  2195: aload_0        
        //  2196: getfield        g.Code:J
        //  2199: invokestatic    java/lang/System.currentTimeMillis:()J
        //  2202: lcmp           
        //  2203: ifge            2930
        //  2206: aconst_null    
        //  2207: putstatic       Code.Code:Lg;
        //  2210: aload_0        
        //  2211: invokevirtual   java/util/TimerTask.cancel:()Z
        //  2214: pop            
        //  2215: getstatic       Code.Code:LCode;
        //  2218: bipush          49
        //  2220: invokestatic    d.I:(I)Ljava/lang/String;
        //  2223: invokevirtual   Code.I:(Ljava/lang/String;)V
        //  2226: return         
        //  2227: aload_0        
        //  2228: getfield        g.Code:Ld;
        //  2231: getfield        d.Code:Z
        //  2234: ifeq            2243
        //  2237: aload_0        
        //  2238: invokevirtual   java/util/TimerTask.cancel:()Z
        //  2241: pop            
        //  2242: return         
        //  2243: getstatic       Code.Code:LCode;
        //  2246: dup            
        //  2247: astore_1       
        //  2248: monitorenter   
        //  2249: aload_0        
        //  2250: getfield        g.Code:Ld;
        //  2253: iconst_0       
        //  2254: invokevirtual   d.Code:(Z)Z
        //  2257: ifeq            2281
        //  2260: aload_0        
        //  2261: getfield        g.Code:Ld;
        //  2264: iconst_1       
        //  2265: invokevirtual   d.Z:(Z)V
        //  2268: aload_0        
        //  2269: getfield        g.Code:Ld;
        //  2272: invokevirtual   d.e:()V
        //  2275: getstatic       Code.Code:LCode;
        //  2278: invokevirtual   javax/microedition/lcdui/Canvas.repaint:()V
        //  2281: aload_1        
        //  2282: monitorexit    
        //  2283: goto            2291
        //  2286: astore_2       
        //  2287: aload_1        
        //  2288: monitorexit    
        //  2289: aload_2        
        //  2290: athrow         
        //  2291: invokestatic    java/lang/System.currentTimeMillis:()J
        //  2294: aload_0        
        //  2295: getfield        g.Code:Ld;
        //  2298: getfield        d.I:J
        //  2301: lsub           
        //  2302: ldc2_w          1000
        //  2305: lrem           
        //  2306: ldc2_w          500
        //  2309: lcmp           
        //  2310: iflt            2317
        //  2313: iconst_1       
        //  2314: goto            2318
        //  2317: iconst_0       
        //  2318: dup            
        //  2319: istore_1       
        //  2320: aload_0        
        //  2321: getfield        g.Code:Ld;
        //  2324: getfield        d.Z:Z
        //  2327: if_icmpeq       2930
        //  2330: aload_0        
        //  2331: getfield        g.Code:Ld;
        //  2334: iload_1        
        //  2335: putfield        d.Z:Z
        //  2338: getstatic       Code.Code:LCode;
        //  2341: invokevirtual   javax/microedition/lcdui/Canvas.repaint:()V
        //  2344: return         
        //  2345: invokestatic    Code.Code:()LB;
        //  2348: aload_0        
        //  2349: getfield        g.Code:LB;
        //  2352: if_acmpne       2930
        //  2355: invokestatic    Code.Code:()Ld;
        //  2358: getfield        d.C:Z
        //  2361: ifne            2930
        //  2364: getstatic       Browser.Code:Ljavax/microedition/lcdui/Display;
        //  2367: invokevirtual   javax/microedition/lcdui/Display.getCurrent:()Ljavax/microedition/lcdui/Displayable;
        //  2370: getstatic       Code.Code:LCode;
        //  2373: if_acmpne       2930
        //  2376: invokestatic    Code.Code:()Z
        //  2379: ifne            2930
        //  2382: aload_0        
        //  2383: invokevirtual   java/util/TimerTask.cancel:()Z
        //  2386: pop            
        //  2387: aload_0        
        //  2388: getfield        g.Code:LB;
        //  2391: invokevirtual   B.i:()V
        //  2394: return         
        //  2395: getstatic       Code.Code:LC;
        //  2398: aload_0        
        //  2399: getfield        g.I:Ljava/lang/String;
        //  2402: invokevirtual   C.I:(Ljava/lang/String;)V
        //  2405: aload_0        
        //  2406: getfield        g.Code:Ld;
        //  2409: invokevirtual   d.Z:()V
        //  2412: aload_0        
        //  2413: getfield        g.Code:Ld;
        //  2416: invokevirtual   d.I:()V
        //  2419: return         
        //  2420: aload_0        
        //  2421: getfield        g.Code:LB;
        //  2424: aload_0        
        //  2425: getfield        g.I:Ljava/lang/String;
        //  2428: getstatic       C.Code:Ljava/lang/String;
        //  2431: invokevirtual   java/lang/String.length:()I
        //  2434: invokevirtual   java/lang/String.substring:(I)Ljava/lang/String;
        //  2437: getstatic       Code.Code:LC;
        //  2440: aload_0        
        //  2441: getfield        g.I:Ljava/lang/String;
        //  2444: invokevirtual   C.Code:(Ljava/lang/String;)I
        //  2447: aload_0        
        //  2448: getfield        g.I:Ljava/lang/String;
        //  2451: invokevirtual   B.Code:(Ljava/lang/String;ILjava/lang/Object;)V
        //  2454: getstatic       Code.Code:LCode;
        //  2457: aload_0        
        //  2458: getfield        g.Code:Ld;
        //  2461: invokevirtual   Code.I:(Ld;)Z
        //  2464: pop            
        //  2465: return         
        //  2466: aload_0        
        //  2467: getfield        g.Code:Ld;
        //  2470: aload_0        
        //  2471: getfield        g.J:Ljava/lang/String;
        //  2474: aload_0        
        //  2475: getfield        g.B:Ljava/lang/String;
        //  2478: aload_0        
        //  2479: getfield        g.Z:Ljava/lang/String;
        //  2482: invokevirtual   d.Code:(Ljava/lang/String;Ljava/lang/String;Ljava/lang/String;)V
        //  2485: aload_0        
        //  2486: getfield        g.Code:Ld;
        //  2489: invokevirtual   d.I:()V
        //  2492: return         
        //  2493: iconst_1       
        //  2494: invokestatic    C.Code:(Z)Z
        //  2497: pop            
        //  2498: getstatic       d.r:Ljava/lang/String;
        //  2501: invokestatic    C.J:(Ljava/lang/String;)V
        //  2504: aload_0        
        //  2505: getfield        g.Code:Ld;
        //  2508: ifnull          2930
        //  2511: aload_0        
        //  2512: getfield        g.Code:Ld;
        //  2515: invokevirtual   d.Z:()V
        //  2518: return         
        //  2519: aload_0        
        //  2520: getfield        g.I:Ljava/lang/String;
        //  2523: invokestatic    C.Z:(Ljava/lang/String;)V
        //  2526: return         
        //  2527: aload_0        
        //  2528: getfield        g.Z:Ljava/lang/String;
        //  2531: ldc             "s"
        //  2533: invokestatic    d.I:(Ljava/lang/String;Ljava/lang/String;)Ljava/lang/String;
        //  2536: astore_1       
        //  2537: aload_0        
        //  2538: getfield        g.Z:Ljava/lang/String;
        //  2541: ifnull          2562
        //  2544: aload_0        
        //  2545: getfield        g.Z:Ljava/lang/String;
        //  2548: ldc             "r"
        //  2550: invokevirtual   java/lang/String.equals:(Ljava/lang/Object;)Z
        //  2553: ifeq            2562
        //  2556: getstatic       d.r:Ljava/lang/String;
        //  2559: invokestatic    C.J:(Ljava/lang/String;)V
        //  2562: aload_0        
        //  2563: getfield        g.Code:LB;
        //  2566: getstatic       d.r:Ljava/lang/String;
        //  2569: aload_1        
        //  2570: ifnonnull       2577
        //  2573: iconst_m1      
        //  2574: goto            2578
        //  2577: iconst_0       
        //  2578: aload_0        
        //  2579: getfield        g.C:Ljava/lang/String;
        //  2582: invokestatic    C.Code:(LB;Ljava/lang/String;ILjava/lang/String;)I
        //  2585: dup            
        //  2586: istore_1       
        //  2587: iconst_1       
        //  2588: if_icmpne       2628
        //  2591: new             Ljava/lang/StringBuffer;
        //  2594: dup            
        //  2595: invokespecial   java/lang/StringBuffer.<init>:()V
        //  2598: sipush          152
        //  2601: invokestatic    d.Code:(I)Ljava/lang/String;
        //  2604: invokevirtual   java/lang/StringBuffer.append:(Ljava/lang/String;)Ljava/lang/StringBuffer;
        //  2607: ldc             " "
        //  2609: invokevirtual   java/lang/StringBuffer.append:(Ljava/lang/String;)Ljava/lang/StringBuffer;
        //  2612: sipush          148
        //  2615: invokestatic    d.Code:(I)Ljava/lang/String;
        //  2618: invokevirtual   java/lang/StringBuffer.append:(Ljava/lang/String;)Ljava/lang/StringBuffer;
        //  2621: invokevirtual   java/lang/StringBuffer.toString:()Ljava/lang/String;
        //  2624: invokestatic    Code.Code:(Ljava/lang/String;)V
        //  2627: return         
        //  2628: iload_1        
        //  2629: iconst_2       
        //  2630: if_icmpne       2930
        //  2633: aload_0        
        //  2634: getfield        g.Code:Ld;
        //  2637: new             Ljava/lang/StringBuffer;
        //  2640: dup            
        //  2641: invokespecial   java/lang/StringBuffer.<init>:()V
        //  2644: ldc             "overlay:"
        //  2646: invokevirtual   java/lang/StringBuffer.append:(Ljava/lang/String;)Ljava/lang/StringBuffer;
        //  2649: sipush          143
        //  2652: invokestatic    d.I:(I)Ljava/lang/String;
        //  2655: invokevirtual   java/lang/StringBuffer.append:(Ljava/lang/String;)Ljava/lang/StringBuffer;
        //  2658: invokevirtual   java/lang/StringBuffer.toString:()Ljava/lang/String;
        //  2661: aconst_null    
        //  2662: aconst_null    
        //  2663: invokevirtual   d.Code:(Ljava/lang/String;Ljava/lang/String;Ljava/lang/String;)V
        //  2666: return         
        //  2667: invokestatic    Code.Code:()Ld;
        //  2670: astore_1       
        //  2671: aload_1        
        //  2672: ifnull          2694
        //  2675: aload_1        
        //  2676: getfield        d.Code:LB;
        //  2679: aload_0        
        //  2680: getfield        g.Code:LB;
        //  2683: if_acmpeq       2694
        //  2686: aload_1        
        //  2687: invokevirtual   d.I:()Ld;
        //  2690: astore_1       
        //  2691: goto            2671
        //  2694: aload_1        
        //  2695: ifnull          2729
        //  2698: aload_0        
        //  2699: getfield        g.Code:LB;
        //  2702: ifnull          2729
        //  2705: getstatic       B.i:I
        //  2708: iconst_1       
        //  2709: iadd           
        //  2710: iconst_3       
        //  2711: irem           
        //  2712: putstatic       B.i:I
        //  2715: aload_0        
        //  2716: getfield        g.Code:LB;
        //  2719: invokevirtual   B.C:()V
        //  2722: getstatic       Code.Code:LCode;
        //  2725: invokevirtual   javax/microedition/lcdui/Canvas.repaint:()V
        //  2728: return         
        //  2729: aload_0        
        //  2730: invokevirtual   java/util/TimerTask.cancel:()Z
        //  2733: pop            
        //  2734: return         
        //  2735: aload_0        
        //  2736: getfield        g.Code:LC;
        //  2739: invokestatic    C.Code:(LC;)V
        //  2742: return         
        //  2743: getstatic       Code.Code:LC;
        //  2746: aload_0        
        //  2747: getfield        g.Code:Ld;
        //  2750: ifnull          2757
        //  2753: iconst_1       
        //  2754: goto            2758
        //  2757: iconst_0       
        //  2758: invokevirtual   C.Code:(Z)V
        //  2761: return         
        //  2762: getstatic       d.B:Ljava/util/Vector;
        //  2765: dup            
        //  2766: astore_1       
        //  2767: monitorenter   
        //  2768: getstatic       d.B:Ljava/util/Vector;
        //  2771: aload_0        
        //  2772: getfield        g.Code:LC;
        //  2775: invokevirtual   java/util/Vector.removeElement:(Ljava/lang/Object;)Z
        //  2778: pop            
        //  2779: getstatic       d.C:Ljava/util/Vector;
        //  2782: aload_0        
        //  2783: getfield        g.Code:LC;
        //  2786: invokevirtual   java/util/Vector.removeElement:(Ljava/lang/Object;)Z
        //  2789: pop            
        //  2790: aload_1        
        //  2791: monitorexit    
        //  2792: goto            2800
        //  2795: astore_2       
        //  2796: aload_1        
        //  2797: monitorexit    
        //  2798: aload_2        
        //  2799: athrow         
        //  2800: sipush          148
        //  2803: iconst_1       
        //  2804: invokestatic    Code.Code:(IZ)Z
        //  2807: pop            
        //  2808: return         
        //  2809: getstatic       Code.Code:LC;
        //  2812: aload_0        
        //  2813: getfield        g.Code:LC;
        //  2816: aload_0        
        //  2817: getfield        g.Code:[Ljava/lang/Object;
        //  2820: invokevirtual   C.Z:(LC;[Ljava/lang/Object;)V
        //  2823: return         
        //  2824: getstatic       Code.Code:LC;
        //  2827: aload_0        
        //  2828: getfield        g.Code:[Ljava/lang/Object;
        //  2831: invokevirtual   C.Code:([Ljava/lang/Object;)Z
        //  2834: ifeq            2930
        //  2837: aload_0        
        //  2838: getfield        g.Code:Ld;
        //  2841: sipush          148
        //  2844: invokestatic    d.I:(I)Ljava/lang/String;
        //  2847: aconst_null    
        //  2848: aconst_null    
        //  2849: invokevirtual   d.Code:(Ljava/lang/String;Ljava/lang/String;Ljava/lang/String;)V
        //  2852: aload_0        
        //  2853: getfield        g.Code:LB;
        //  2856: ifnull          2930
        //  2859: aload_0        
        //  2860: getfield        g.Code:LB;
        //  2863: iconst_0       
        //  2864: putfield        B.e:Z
        //  2867: return         
        //  2868: getstatic       Code.Code:LCode;
        //  2871: invokevirtual   javax/microedition/lcdui/Canvas.repaint:()V
        //  2874: return         
        //  2875: getstatic       Code.Code:LCode;
        //  2878: dup            
        //  2879: astore_1       
        //  2880: monitorenter   
        //  2881: getstatic       Code.Code:LCode;
        //  2884: getfield        Code.Code:Ljava/lang/Object;
        //  2887: checkcast       Ld;
        //  2890: astore_2       
        //  2891: aload_0        
        //  2892: getfield        g.Code:I
        //  2895: getstatic       Code.Code:LCode;
        //  2898: getfield        Code.b:I
        //  2901: if_icmpne       2912
        //  2904: aload_2        
        //  2905: ifnull          2912
        //  2908: aload_2        
        //  2909: invokevirtual   d.B:()V
        //  2912: aload_1        
        //  2913: monitorexit    
        //  2914: return         
        //  2915: astore_2       
        //  2916: aload_1        
        //  2917: monitorexit    
        //  2918: aload_2        
        //  2919: athrow         
        //  2920: instanceof      Ljava/lang/OutOfMemoryError;
        //  2923: ifeq            2930
        //  2926: iconst_2       
        //  2927: invokestatic    Code.Code:(I)V
        //  2930: return         
        //    StackMap: 00 7B 00 DC 00 00 00 00 00 E3 00 00 00 00 00 EA 00 00 00 00 00 F7 00 00 00 00 01 01 00 00 00 00 01 3F 00 01 07 00 13 00 00 01 5D 00 02 07 00 13 07 00 1B 00 00 01 83 00 02 07 00 13 07 00 1B 00 00 01 87 00 02 07 00 13 07 00 1B 00 01 07 00 23 01 B2 00 00 00 01 07 00 1A 01 B4 00 00 00 00 01 C1 00 01 07 00 13 00 00 01 DE 00 02 07 00 13 07 00 13 00 00 01 EC 00 02 00 07 00 13 00 01 07 00 1F 01 F1 00 03 07 00 13 00 07 00 0C 00 00 01 FF 00 00 00 00 02 0A 00 01 07 00 13 00 00 02 1E 00 02 07 00 13 07 00 13 00 00 02 23 00 02 00 07 00 13 00 01 07 00 1F 02 28 00 01 07 00 13 00 00 02 3B 00 01 07 00 13 00 00 02 A9 00 0D 07 00 13 07 00 17 07 00 14 07 00 1B 07 00 1B 01 01 01 01 01 01 07 00 1B 07 00 1B 00 00 02 E8 00 02 07 00 13 07 00 17 00 00 02 FC 00 0E 07 00 13 07 00 17 07 00 14 07 00 1B 07 00 1B 01 01 01 01 01 01 07 00 1B 07 00 1B 01 00 00 03 34 00 12 07 00 13 07 00 17 07 00 14 07 00 1B 07 00 1B 01 01 01 01 01 01 07 00 1B 07 00 1B 01 01 05 05 07 00 22 00 00 03 51 00 12 07 00 13 07 00 17 07 00 14 07 00 1B 07 00 1B 01 01 01 01 01 01 07 00 1B 07 00 1B 01 01 00 05 07 00 22 00 00 03 63 00 13 07 00 13 07 00 17 07 00 14 07 00 1B 07 00 1B 01 01 01 01 01 01 07 00 1B 07 00 1B 01 01 07 00 22 05 07 00 22 01 00 00 03 94 00 15 07 00 13 07 00 17 07 00 14 07 00 1B 07 00 1B 01 01 01 01 01 01 07 00 1B 07 00 1B 01 01 07 00 22 05 07 00 22 01 07 00 11 01 00 00 03 B8 00 14 07 00 13 07 00 17 07 00 14 07 00 1B 07 00 1B 01 01 01 01 01 01 07 00 1B 07 00 1B 01 01 07 00 22 05 07 00 22 01 07 00 11 00 00 03 C5 00 12 07 00 13 07 00 17 07 00 14 07 00 1B 07 00 1B 01 01 01 01 01 01 07 00 1B 07 00 1B 01 01 07 00 22 05 07 00 22 00 00 03 CA 00 12 07 00 13 07 00 17 07 00 14 07 00 1B 07 00 1B 01 01 01 01 01 01 07 00 1B 07 00 1B 01 01 07 00 22 05 07 00 22 00 00 03 DD 00 13 07 00 13 07 00 17 07 00 14 07 00 1B 07 00 1B 01 01 01 01 01 01 07 00 1B 07 00 1B 01 01 07 00 22 07 00 22 07 00 22 01 00 00 03 FE 00 13 07 00 13 07 00 17 07 00 14 07 00 1B 07 00 1B 01 01 01 01 01 01 07 00 1B 07 00 1B 01 01 07 00 22 07 00 22 07 00 22 01 00 00 04 0D 00 13 07 00 13 07 00 17 07 00 14 07 00 1B 07 00 1B 01 01 01 01 01 01 07 00 1B 07 00 1B 01 01 07 00 22 07 00 22 07 00 22 01 00 00 04 1A 00 14 07 00 13 07 00 17 07 00 14 07 00 1B 07 00 1B 01 01 01 01 01 01 07 00 1B 07 00 1B 01 01 07 00 22 07 00 22 07 00 22 01 07 00 11 00 00 04 35 00 14 07 00 13 07 00 17 07 00 14 07 00 1B 07 00 1B 01 01 01 01 01 01 07 00 1B 07 00 1B 01 01 07 00 22 07 00 22 07 00 22 01 07 00 11 00 00 04 4F 00 12 07 00 13 07 00 17 07 00 14 07 00 1B 07 00 1B 01 00 01 01 01 01 07 00 1B 07 00 1B 01 01 07 00 22 07 00 22 07 00 22 00 00 04 52 00 12 07 00 13 07 00 17 07 00 14 07 00 1B 07 00 1B 01 01 01 01 01 01 07 00 1B 07 00 1B 01 01 07 00 22 07 00 22 07 00 22 00 00 04 A2 00 17 07 00 13 07 00 17 07 00 14 07 00 1B 07 00 1B 01 01 01 01 01 01 07 00 1B 07 00 1B 01 01 07 00 22 07 00 22 07 00 22 01 01 01 01 07 00 10 00 00 04 B2 00 16 07 00 13 07 00 17 07 00 14 07 00 1B 07 00 1B 01 01 01 01 01 01 07 00 1B 07 00 1B 01 01 07 00 22 07 00 22 07 00 22 01 01 01 01 00 00 04 D1 00 02 07 00 13 07 00 17 00 00 04 E5 00 18 07 00 13 07 00 17 07 00 14 07 00 1B 07 00 1B 01 01 01 01 01 01 07 00 1B 07 00 1B 01 01 07 00 22 07 00 22 07 00 22 01 01 01 01 00 07 00 11 00 01 01 04 F6 00 18 07 00 13 07 00 17 07 00 14 07 00 1B 07 00 1B 01 01 01 01 01 01 07 00 1B 07 00 1B 01 01 07 00 22 07 00 22 07 00 22 01 01 01 01 07 00 10 07 00 11 00 00 05 08 00 18 07 00 13 07 00 17 07 00 14 07 00 1B 07 00 1B 01 01 01 01 01 01 07 00 1B 07 00 1B 01 01 07 00 22 07 00 22 07 00 22 01 01 01 01 07 00 10 07 00 11 00 00 05 0E 00 18 07 00 13 07 00 17 07 00 14 07 00 1B 07 00 1B 01 01 01 01 01 01 07 00 1B 07 00 1B 01 01 07 00 22 07 00 22 07 00 22 01 01 01 01 07 00 10 07 00 11 00 00 05 21 00 18 07 00 13 07 00 17 07 00 14 07 00 1B 07 00 1B 01 01 01 01 01 01 07 00 1B 07 00 1B 01 01 07 00 22 07 00 22 07 00 22 01 01 01 01 07 00 10 07 00 11 00 00 05 27 00 18 07 00 13 07 00 17 07 00 14 07 00 1B 07 00 1B 01 01 01 01 01 01 07 00 1B 07 00 1B 01 01 07 00 22 07 00 22 07 00 22 01 01 01 01 07 00 10 07 00 11 00 00 05 49 00 1A 07 00 13 07 00 17 07 00 14 07 00 1B 07 00 1B 01 01 01 01 01 01 07 00 1B 07 00 1B 01 01 07 00 22 07 00 22 07 00 22 01 01 01 01 07 00 10 07 00 11 00 07 00 10 00 00 05 52 00 18 07 00 13 07 00 17 07 00 14 07 00 1B 07 00 1B 01 01 01 01 01 01 07 00 1B 07 00 1B 01 01 07 00 22 07 00 22 07 00 22 01 01 01 01 07 00 10 07 00 11 00 00 05 57 00 18 07 00 13 07 00 17 07 00 14 07 00 1B 07 00 1B 01 01 01 01 01 01 07 00 1B 07 00 1B 01 01 07 00 22 07 00 22 07 00 22 01 01 01 01 07 00 10 07 00 11 00 00 05 70 00 18 07 00 13 07 00 17 07 00 14 07 00 1B 07 00 1B 01 01 01 01 01 01 07 00 1B 07 00 1B 01 01 07 00 22 07 00 22 07 00 22 00 01 00 01 07 00 10 07 00 11 00 00 05 8A 00 19 07 00 13 07 00 17 07 00 14 07 00 1B 07 00 1B 01 01 01 01 01 01 07 00 1B 07 00 1B 01 01 07 00 22 07 00 22 07 00 22 01 01 00 01 07 00 10 07 00 11 01 00 00 05 A8 00 18 07 00 13 07 00 17 07 00 14 07 00 1B 07 00 1B 01 01 01 01 01 01 07 00 1B 07 00 1B 01 01 07 00 22 07 00 22 07 00 22 01 01 00 01 07 00 10 07 00 11 00 00 05 C7 00 18 07 00 13 07 00 17 07 00 14 07 00 1B 07 00 1B 01 01 01 01 01 01 07 00 1B 07 00 1B 01 01 07 00 22 07 00 22 07 00 22 00 01 00 01 07 00 10 07 00 11 00 00 05 D5 00 18 07 00 13 07 00 17 07 00 14 07 00 1B 07 00 1B 01 01 01 01 01 01 07 00 1B 07 00 1B 01 01 07 00 22 07 00 22 07 00 22 00 00 00 01 07 00 10 07 00 11 00 00 06 06 00 16 07 00 13 07 00 17 07 00 14 07 00 1B 07 00 1B 01 01 01 01 01 01 07 00 1B 07 00 1B 01 01 07 00 22 07 00 22 07 00 22 00 01 00 01 00 00 06 1D 00 18 07 00 13 07 00 17 07 00 14 07 00 1B 07 00 1B 01 01 01 01 01 01 07 00 1B 07 00 1B 01 01 07 00 22 07 00 22 07 00 22 01 01 00 00 00 07 00 11 00 00 06 4F 00 18 07 00 13 07 00 17 07 00 14 07 00 1B 07 00 1B 01 01 01 01 01 01 07 00 1B 07 00 1B 01 01 07 00 22 07 00 22 07 00 22 00 00 00 00 00 07 00 11 00 00 06 64 00 12 07 00 13 07 00 17 07 00 14 07 00 1B 07 00 1B 01 01 01 01 01 01 07 00 1B 07 00 1B 01 01 07 00 22 07 00 22 07 00 22 00 00 06 6A 00 12 07 00 13 07 00 17 00 07 00 1B 07 00 1B 01 00 01 01 01 01 07 00 1B 07 00 1B 00 01 07 00 22 07 00 22 07 00 22 00 00 06 75 00 12 07 00 13 07 00 17 00 07 00 1B 07 00 1B 01 00 01 01 01 01 07 00 1B 07 00 1B 00 01 07 00 22 07 00 22 07 00 22 00 00 06 7C 00 12 07 00 13 07 00 17 01 07 00 1B 07 00 1B 01 00 01 01 01 01 07 00 1B 07 00 1B 00 01 07 00 22 07 00 22 07 00 22 00 00 06 D7 00 12 07 00 13 07 00 17 01 07 00 1B 07 00 1B 01 00 01 01 01 01 07 00 1B 07 00 1B 00 00 07 00 22 07 00 22 07 00 22 00 00 06 E9 00 12 07 00 13 07 00 17 01 07 00 1B 07 00 1B 01 00 01 01 01 01 07 00 1B 07 00 1B 00 01 07 00 22 07 00 22 07 00 22 00 00 06 EF 00 12 07 00 13 07 00 17 00 07 00 1B 07 00 1B 01 00 01 01 01 01 07 00 1B 07 00 1B 00 01 05 05 07 00 22 00 00 06 FC 00 12 07 00 13 07 00 17 00 07 00 1B 07 00 1B 01 00 01 01 01 01 07 00 1B 07 00 1B 00 01 07 00 22 07 00 22 07 00 22 00 00 07 29 00 12 07 00 13 07 00 17 00 00 07 00 1B 01 00 01 01 01 01 07 00 1B 07 00 1B 00 01 07 00 22 07 00 22 07 00 22 00 00 07 3D 00 12 07 00 13 07 00 17 00 00 07 00 1B 01 00 01 01 00 01 07 00 1B 07 00 1B 00 01 00 07 00 22 07 00 22 00 00 07 4E 00 12 07 00 13 07 00 17 01 00 07 00 1B 01 00 01 00 00 01 07 00 1B 07 00 1B 00 01 00 00 07 00 22 00 00 07 6A 00 0F 07 00 13 07 00 17 00 00 07 00 1B 01 00 01 00 00 01 07 00 1B 07 00 1B 00 01 00 00 07 7F 00 0F 07 00 13 07 00 17 00 00 07 00 1B 01 00 01 00 00 01 07 00 1B 00 00 01 00 00 07 80 00 0F 07 00 13 07 00 17 00 00 07 00 1B 01 00 01 00 00 01 07 00 1B 00 00 01 00 01 01 07 94 00 0F 07 00 13 07 00 17 00 00 07 00 1B 01 00 00 00 00 01 00 00 00 01 00 00 07 9E 00 0F 07 00 13 07 00 17 00 00 07 00 1B 00 00 00 00 00 01 00 00 00 01 00 00 07 B5 00 0B 07 00 13 07 00 17 00 00 00 00 00 00 00 00 01 00 00 07 F4 00 02 07 00 13 07 00 17 00 00 08 08 00 02 07 00 13 07 00 17 00 01 07 00 1F 08 1C 00 02 00 07 00 17 00 00 08 1F 00 02 00 07 00 17 00 01 07 00 1F 08 24 00 01 07 00 13 00 00 08 5B 00 00 00 01 07 00 1F 08 5C 00 00 00 00 08 67 00 01 07 00 13 00 00 08 74 00 01 07 00 13 00 00 08 8D 00 01 07 00 13 00 00 08 B3 00 01 07 00 13 00 00 08 C3 00 01 07 00 13 00 00 08 E9 00 02 07 00 13 07 00 0F 00 00 08 EE 00 02 00 07 00 0F 00 01 07 00 1F 08 F3 00 01 07 00 13 00 00 09 0D 00 01 07 00 13 00 00 09 0E 00 01 07 00 13 00 01 01 09 29 00 01 07 00 13 00 00 09 5B 00 01 07 00 13 00 00 09 65 00 01 07 00 13 00 00 09 74 00 01 07 00 13 00 00 09 A2 00 01 07 00 13 00 00 09 BD 00 01 07 00 13 00 00 09 D7 00 01 07 00 13 00 00 09 DF 00 01 07 00 13 00 00 0A 02 00 02 07 00 13 07 00 1B 00 00 0A 11 00 01 07 00 13 00 02 07 00 0C 07 00 1B 0A 12 00 01 07 00 13 00 03 07 00 0C 07 00 1B 01 0A 44 00 02 07 00 13 01 00 00 0A 6B 00 01 07 00 13 00 00 0A 6F 00 02 07 00 13 07 00 12 00 00 0A 86 00 02 07 00 13 07 00 12 00 00 0A A9 00 01 07 00 13 00 00 0A AF 00 01 07 00 13 00 00 0A B7 00 01 07 00 13 00 00 0A C5 00 00 00 01 07 00 0E 0A C6 00 00 00 02 07 00 0E 01 0A CA 00 01 07 00 13 00 00 0A EB 00 02 00 07 00 22 00 01 07 00 1F 0A F0 00 00 00 00 0A F9 00 01 07 00 13 00 00 0B 08 00 01 07 00 13 00 00 0B 34 00 00 00 00 0B 3B 00 01 07 00 13 00 00 0B 60 00 02 00 07 00 0F 00 00 0B 63 00 02 00 07 00 0F 00 01 07 00 1F 0B 68 00 00 00 01 07 00 1F 0B 72 00 00 00 00
        //    Exceptions:
        //  Try           Handler
        //  Start  End    Start  End    Type                                               
        //  -----  -----  -----  -----  ---------------------------------------------------
        //  331    390    391    434    Ljavax/microedition/io/ConnectionNotFoundException;
        //  331    390    434    436    Ljava/lang/SecurityException;
        //  475    478    492    497    Any
        //  539    542    547    552    Any
        //  223    577    2920   2930   Any
        //  584    744    2056   2076   Any
        //  748    761    2079   2084   Any
        //  773    1226   2056   2076   Any
        //  1237   1250   2079   2084   Any
        //  1253   2035   2056   2076   Any
        //  2040   2076   2079   2084   Any
        //  2098   2135   2139   2140   Any
        //  2254   2281   2286   2291   Any
        //  2775   2789   2795   2800   Any
        //  2887   2912   2915   2920   Any
        //  2083   2920   2920   2930   Any
        // 
        // The error that occurred was:
        // 
        // java.lang.IllegalStateException: Expression is linked from several locations: Label_0764:
        //     at com.strobel.decompiler.ast.Error.expressionLinkedFromMultipleLocations(Error.java:27)
        //     at com.strobel.decompiler.ast.AstOptimizer.mergeDisparateObjectInitializations(AstOptimizer.java:2596)
        //     at com.strobel.decompiler.ast.AstOptimizer.optimize(AstOptimizer.java:235)
        //     at com.strobel.decompiler.ast.AstOptimizer.optimize(AstOptimizer.java:42)
        //     at com.strobel.decompiler.languages.java.ast.AstMethodBodyBuilder.createMethodBody(AstMethodBodyBuilder.java:214)
        //     at com.strobel.decompiler.languages.java.ast.AstMethodBodyBuilder.createMethodBody(AstMethodBodyBuilder.java:99)
        //     at com.strobel.decompiler.languages.java.ast.AstBuilder.createMethodBody(AstBuilder.java:782)
        //     at com.strobel.decompiler.languages.java.ast.AstBuilder.createMethod(AstBuilder.java:675)
        //     at com.strobel.decompiler.languages.java.ast.AstBuilder.addTypeMembers(AstBuilder.java:552)
        //     at com.strobel.decompiler.languages.java.ast.AstBuilder.createTypeCore(AstBuilder.java:519)
        //     at com.strobel.decompiler.languages.java.ast.AstBuilder.createTypeNoCache(AstBuilder.java:161)
        //     at com.strobel.decompiler.languages.java.ast.AstBuilder.createType(AstBuilder.java:150)
        //     at com.strobel.decompiler.languages.java.ast.AstBuilder.addType(AstBuilder.java:125)
        //     at com.strobel.decompiler.languages.java.JavaLanguage.buildAst(JavaLanguage.java:71)
        //     at com.strobel.decompiler.languages.java.JavaLanguage.decompileType(JavaLanguage.java:59)
        //     at com.strobel.decompiler.DecompilerDriver.decompileType(DecompilerDriver.java:330)
        //     at com.strobel.decompiler.DecompilerDriver.decompileJar(DecompilerDriver.java:251)
        //     at com.strobel.decompiler.DecompilerDriver.main(DecompilerDriver.java:126)
        // 
        throw new IllegalStateException("An error occurred while decompiling this method.");
    }
    
    static synchronized void Code() {
        if (g.I == null) {
            g.I = new g(27);
            new Thread(g.I).start();
        }
        // monitorenter(i = g.I)
        g.J = true;
        final g j = g.I;
        try {
            j.notify();
        }
        finally {
        }
        // monitorexit(i)
    }
    
    static synchronized void Code(final B code) {
        if (!d.k) {
            if (g.Code == null) {
                g.Code = new g(23);
                final Thread thread;
                (thread = new Thread(g.Code)).setPriority(1);
                thread.start();
            }
            // monitorenter(code2 = g.Code)
            g.Code.Code = code;
            g.Z = true;
            final g code3 = g.Code;
            try {
                code3.notify();
            }
            finally {
            }
            // monitorexit(code2)
        }
    }
    
    static void Z() {
        Code.Code = null;
    }
    
    static void I() {
        (Code.Code = new g(32)).Code = System.currentTimeMillis() + 10000L;
        Code.Code.Code.schedule(Code.Code, 10000L, 2000L);
    }
    
    static void J() {
        final B code = Code.Code();
        if (g.Z != null) {
            if (g.Z.Code == code) {
                return;
            }
            g.Z.cancel();
            g.Z = null;
        }
        if (code != null && code.C != null) {
            (g.Z = new g(34)).Code = code;
            Code.Code.Code.schedule(g.Z, code.j, 2000L);
        }
    }
    
    static {
        g.Code = new Object();
    }
}
